mypyc_ipython/__init__.py
mypyc_ipython/_magic.py
mypyc_ipython-0.0.2.dist-info/LICENSE
mypyc_ipython-0.0.2.dist-info/METADATA
mypyc_ipython-0.0.2.dist-info/WHEEL
mypyc_ipython-0.0.2.dist-info/top_level.txt
mypyc_ipython-0.0.2.dist-info/RECORD
