Metadata-Version: 2.1
Name: mypyc-ipython
Version: 0.0.2
Summary: IPython magic command interface for interactive work with mypyc.
Home-page: https://github.com/c-bata/mypyc-ipython
Author: Masashi Shibata
Author-email: m.sh.nwpct1@gmail.com
License: MIT License
Platform: UNKNOWN
Classifier: Development Status :: 2 - Pre-Alpha
Classifier: Intended Audience :: Developers
Classifier: License :: OSI Approved :: MIT License
Classifier: Programming Language :: Python
Classifier: Programming Language :: Python :: 3
Classifier: Programming Language :: Python :: 3.6
Classifier: Programming Language :: Python :: 3.7
Classifier: Programming Language :: Python :: 3.8
Classifier: Programming Language :: Python :: 3 :: Only
Requires-Python: >=3.6
Requires-Dist: mypy (>=0.800)
Requires-Dist: ipython
